open_groceries/__init__.py
open_groceries/adapters/__init__.py
open_groceries/adapters/costco.py
open_groceries/adapters/wegmans.py
open_groceries/exceptions.py
open_groceries/models/__init__.py
open_groceries/models/adapter.py
open_groceries/models/groceries.py
open_groceries/models/location.py
open_groceries/models/store.py
open_groceries-0.3.2.dist-info/LICENSE
open_groceries-0.3.2.dist-info/METADATA
open_groceries-0.3.2.dist-info/WHEEL
open_groceries-0.3.2.dist-info/RECORD
