Metadata-Version: 2.1
Name: open-groceries
Version: 0.3.2
Summary: Unified data acquisition across multiple grocery store sites
Home-page: https://github.com/iTecAI/open-groceries
License: MIT
Keywords: requests,modular,groceries,web,web scraping
Author: Dax Harris
Author-email: matteovh@gmail.com
Requires-Python: >=3.11,<4.0
Classifier: Development Status :: 4 - Beta
Classifier: License :: OSI Approved :: MIT License
Classifier: Programming Language :: Python :: 3
Classifier: Programming Language :: Python :: 3.11
Classifier: Topic :: Internet :: WWW/HTTP :: Indexing/Search
Requires-Dist: bs4 (>=0.0.1,<0.0.2)
Requires-Dist: esprima (>=4.0.1,<5.0.0)
Requires-Dist: requests (>=2.31.0,<3.0.0)
Project-URL: Repository, https://github.com/iTecAI/open-groceries
